asthook/__init__.py
asthook/__main__.py
asthook/asthook_server_ast.py
asthook/bootstrap.py
asthook/conf.py
asthook/config.py
asthook/log.py
asthook/logo.ans
asthook/myadb.py
asthook/parser.py
asthook/bin/Frida.zip
asthook/dynamic/__init__.py
asthook/dynamic/cmd.py
asthook/dynamic/frida.py
asthook/dynamic/mmodule.py
asthook/dynamic/module/__init__.py
asthook/dynamic/module/register.py
asthook/dynamic/module/AWS/__init__.py
asthook/dynamic/module/Antiroot/__init__.py
asthook/dynamic/module/Ble_sniff/__init__.py
asthook/dynamic/module/GitFilesStore/__init__.py
asthook/dynamic/module/NativeHook/__init__.py
asthook/dynamic/module/PreventFilesDeleted/__init__.py
asthook/dynamic/module/QuickHook/__init__.py
asthook/dynamic/module/SSLpinning/__init__.py
asthook/dynamic/module/Shell/__init__.py
asthook/script_frida/blemon.js
asthook/script_frida/file_del.js
asthook/script_frida/generalinfo.js
asthook/script_frida/hookfile.js
asthook/script_frida/hookfile2.js
asthook/script_frida/hooknative.js
asthook/script_frida/objection.js
asthook/script_frida/root_bypass.js
asthook/script_frida/socket.js
asthook/script_frida/sslpinning.js
asthook/static/__init__.py
asthook/static/decompiler.py
asthook/static/manifest.py
asthook/static/ast/AstInRam.py
asthook/static/ast/Taint.py
asthook/static/ast/__init__.py
asthook/static/generate_apk/__init__.py
asthook/static/module/__init__.py
asthook/static/module/register.py
asthook/static/module/ApiKeyDetector/__init__.py
asthook/static/module/ApiKeyDetector/keys.py
asthook/static/module/Basic_Vulns/__init__.py
asthook/static/module/Basic_Vulns/basic_vulns.py
asthook/static/module/CheckJavascript/__init__.py
asthook/static/module/CheckJavascript/check_javascript.py
asthook/static/module/CloudAnalysis/__init__.py
asthook/static/module/GenHook/GenHook_node.py
asthook/static/module/GenHook/__init__.py
asthook/static/module/ListFuncs/ListFuncs_node.py
asthook/static/module/ListFuncs/__init__.py
asthook-1.0.17.dist-info/AUTHORS
asthook-1.0.17.dist-info/COPYING
asthook-1.0.17.dist-info/LICENSE
asthook-1.0.17.dist-info/METADATA
asthook-1.0.17.dist-info/WHEEL
asthook-1.0.17.dist-info/entry_points.txt
asthook-1.0.17.dist-info/top_level.txt
asthook-1.0.17.dist-info/RECORD
