Metadata-Version: 2.1
Name: asthook
Version: 1.0.17
Summary: Analyse apk source code and make a dynamic analysis
Author-email: "Benoit Forgette (MadSquirrel)" <benoit.forgette@ci-yow.com>
Maintainer-email: "Benoit Forgette (MadSquirrel)" <benoit.forgette@ci-yow.com>
License: GNU GENERAL PUBLIC LICENSE
Project-URL: Homepage, https://ci-yow.com
Project-URL: Repository, https://gitlab.com/MadSquirrels/mobile/asthook
Project-URL: Documentation, https://madsquirrels.gitlab.io/mobile/asthook/
Project-URL: Issues, https://gitlab.com/MadSquirrels/mobile/asthook/-/issues
Classifier: Development Status :: 4 - Beta
Classifier: Programming Language :: Python
Requires-Python: >=3.5
License-File: LICENSE
License-File: COPYING
License-File: AUTHORS
Requires-Dist: Pillow ==6.2.2
Requires-Dist: pure-python-adb
Requires-Dist: pyyaml
Requires-Dist: sty
Requires-Dist: graphviz
Requires-Dist: shutils
Requires-Dist: jinja2
Requires-Dist: gitpython
Requires-Dist: javalang
Requires-Dist: apk2java
Requires-Dist: frida ==16.3.3
Requires-Dist: requests
Requires-Dist: Matplotlib
Requires-Dist: tabulate
Requires-Dist: apkpatcher >=0.1.9
